nonebot_plugin_blockwords/__init__.py
nonebot_plugin_blockwords/check.py
nonebot_plugin_blockwords/config.py
nonebot_plugin_blockwords/exception.py
nonebot_plugin_blockwords/hook/__init__.py
nonebot_plugin_blockwords/hook/bot.py
nonebot_plugin_blockwords/matcher.py
nonebot_plugin_blockwords/params.py
nonebot_plugin_blockwords/typings.py
nonebot_plugin_blockwords/utils.py
nonebot_plugin_blockwords-0.2.1.dist-info/LICENSE
nonebot_plugin_blockwords-0.2.1.dist-info/METADATA
nonebot_plugin_blockwords-0.2.1.dist-info/WHEEL
nonebot_plugin_blockwords-0.2.1.dist-info/RECORD
