Metadata-Version: 2.1
Name: nonebot-plugin-blockwords
Version: 0.2.1
Summary: nonebot聊天屏蔽词插件
License: MIT
Keywords: bot,nonebot2,nonebot-plugin,blockwords
Author: MelodyKnit
Author-email: 2711402357@qq.com
Requires-Python: >=3.8,<4.0
Classifier: License :: OSI Approved :: MIT License
Classifier: Programming Language :: Python :: 3
Classifier: Programming Language :: Python :: 3.8
Classifier: Programming Language :: Python :: 3.9
Classifier: Programming Language :: Python :: 3.10
Classifier: Programming Language :: Python :: 3.11
Requires-Dist: jieba (>=0.42.1,<0.43.0)
Requires-Dist: nonebot2 (>=2.1.1,<3.0.0)
